rougail/user_data_file/__init__.py
rougail/user_data_file/config.py
rougail/user_data_file/i18n.py
rougail/user_data_file/locale/fr/LC_MESSAGES/user_data_file.mo
rougail_user_data_file-0.1.0.dist-info/LICENSE
rougail_user_data_file-0.1.0.dist-info/WHEEL
rougail_user_data_file-0.1.0.dist-info/METADATA
rougail_user_data_file-0.1.0.dist-info/RECORD
